gfpa/__init__.py
gfpa/plotting.py
gfpa/preprocessing.py
gfpa/table.py
gfpa/tools.py
gfpa-1.1.0.dist-info/LICENSE.txt
gfpa-1.1.0.dist-info/METADATA
gfpa-1.1.0.dist-info/WHEEL
gfpa-1.1.0.dist-info/top_level.txt
gfpa-1.1.0.dist-info/RECORD
